.gitignore
README.md
setup.py
WebHDFS.egg-info/PKG-INFO
WebHDFS.egg-info/SOURCES.txt
WebHDFS.egg-info/dependency_links.txt
WebHDFS.egg-info/entry_points.txt
WebHDFS.egg-info/top_level.txt
webhdfs/VERSION
webhdfs/__init__.py
webhdfs/example.py
webhdfs/webhdfs.py