Metadata-Version: 1.1
Name: WebHDFS
Version: 0.2.0
Summary: HDFS Python client based on WebHDFS REST API
Home-page: na
Author: Andre Luckow
Author-email: andre.luckow@gmail.com
License: UNKNOWN
Platform: Unix
Platform: Linux
Platform: Mac OS
Classifier: Development Status :: 4 - Beta
Classifier: Programming Language :: Python
Classifier: Environment :: Console
Classifier: Topic :: Utilities
